RetroGeo/KD_Tree.py
RetroGeo/__init__.py
RetroGeo/retro_geo.py
RetroGeo/test_retro_geo.py
RetroGeo/thread_typ.py
locatr/KD_Tree.py
locatr/__init__.py
locatr/locatr.py
locatr/main.py
locatr/rgeo.py
locatr/test_locatr.py
locatr/thread_typ.py
locatr/thread_typ_enum.py
RetroGeo-0.1.dist-info/METADATA
RetroGeo-0.1.dist-info/WHEEL
RetroGeo-0.1.dist-info/top_level.txt
RetroGeo-0.1.dist-info/RECORD
