Metadata-Version: 2.1
Name: RetroGeo
Version: 0.1
Summary: RetroGeo:  A simple offline Reverse Geocoder Library
Author: SOORAJ TS
Author-email: sjts007@gmail.com
Keywords: reverse geocoding,geolocation,offline,python
Classifier: Development Status :: 4 - Beta
Classifier: Intended Audience :: Developers
Classifier: Topic :: Software Development :: Libraries :: Python Modules
Classifier: License :: OSI Approved :: MIT License
Classifier: Programming Language :: Python :: 3
Classifier: Operating System :: OS Independent
Requires-Dist: aiocache==0.12.2
Requires-Dist: annotated-types==0.7.0
Requires-Dist: anyio==4.4.0
Requires-Dist: certifi==2024.8.30
Requires-Dist: charset-normalizer==3.3.2
Requires-Dist: docutils==0.21.2
Requires-Dist: h11==0.14.0
Requires-Dist: httpcore==1.0.5
Requires-Dist: httpx==0.27.2
Requires-Dist: idna==3.8
Requires-Dist: importlib-metadata==8.4.0
Requires-Dist: jaraco.classes==3.4.0
Requires-Dist: jaraco.context==6.0.1
Requires-Dist: jaraco.functools==4.0.2
Requires-Dist: keyring==25.3.0
Requires-Dist: markdown-it-py==3.0.0
Requires-Dist: mdurl==0.1.2
Requires-Dist: more-itertools==10.5.0
Requires-Dist: nh3==0.2.18
Requires-Dist: numpy==2.1.1
Requires-Dist: pandas==2.2.2
Requires-Dist: pkginfo==1.10.0
Requires-Dist: pydantic==2.9.0
Requires-Dist: pydantic-core==2.23.2
Requires-Dist: Pygments==2.18.0
Requires-Dist: python-dateutil==2.9.0.post0
Requires-Dist: pytz==2024.1
Requires-Dist: readme-renderer==44.0
Requires-Dist: requests==2.32.3
Requires-Dist: requests-toolbelt==1.0.0
Requires-Dist: rfc3986==2.0.0
Requires-Dist: rich==13.8.0
Requires-Dist: scipy==1.14.1
Requires-Dist: setuptools==74.1.2
Requires-Dist: six==1.16.0
Requires-Dist: sniffio==1.3.1
Requires-Dist: typing-extensions==4.12.2
Requires-Dist: tzdata==2024.1
Requires-Dist: urllib3==2.2.2
Requires-Dist: zipp==3.20.1
